multimatcher/__init__.py
multimatcher/match.py
multimatcher/match_mode.py
multimatcher/matcher.py
multimatcher/replacer.py
multimatcher/trie.py
multimatcher-0.0.3.dist-info/LICENSE
multimatcher-0.0.3.dist-info/METADATA
multimatcher-0.0.3.dist-info/WHEEL
multimatcher-0.0.3.dist-info/top_level.txt
multimatcher-0.0.3.dist-info/RECORD
