Metadata-Version: 2.1
Name: multimatcher
Version: 0.0.3
Summary: A convenient implementation of the Aho-Corasick algorithm to efficiently find multiple search patterns and process the matches
Author-email: Muhammad Khattab <muhammad.khattab@hotmail.com>
Project-URL: Homepage, https://github.com/mmkhattab/multimatcher
Project-URL: Bug Tracker, https://github.com/mmkhattab/multimatcher/issues
Classifier: Programming Language :: Python :: 3
Classifier: License :: OSI Approved :: MIT License
Classifier: Operating System :: OS Independent
Requires-Python: >=3.8
License-File: LICENSE
Requires-Dist: requests
Requires-Dist: importlib-metadata ; python_version >= "3.8"
